cyberfusion/RabbitMQConsumer/__init__.py
cyberfusion/RabbitMQConsumer/config.py
cyberfusion/RabbitMQConsumer/contracts.py
cyberfusion/RabbitMQConsumer/exceptions.py
cyberfusion/RabbitMQConsumer/log_server_client.py
cyberfusion/RabbitMQConsumer/models.py
cyberfusion/RabbitMQConsumer/processor.py
cyberfusion/RabbitMQConsumer/pydantic_types.py
cyberfusion/RabbitMQConsumer/rabbitmq.py
cyberfusion/RabbitMQConsumer/rabbitmq_consume.py
cyberfusion/RabbitMQConsumer/types.py
cyberfusion/RabbitMQConsumer/utilities.py
cyberfusion/RabbitMQHandlers/exchanges/dx_example/__init__.py
python3_cyberfusion_rabbitmq_consumer-3.1.dist-info/METADATA
python3_cyberfusion_rabbitmq_consumer-3.1.dist-info/WHEEL
python3_cyberfusion_rabbitmq_consumer-3.1.dist-info/entry_points.txt
python3_cyberfusion_rabbitmq_consumer-3.1.dist-info/top_level.txt
python3_cyberfusion_rabbitmq_consumer-3.1.dist-info/RECORD
