Metadata-Version: 2.4
Name: python3-cyberfusion-rabbitmq-consumer
Version: 3.1
Summary: Lean RPC framework based on RabbitMQ.
Author-email: Cyberfusion <support@cyberfusion.io>
Project-URL: Source, https://github.com/CyberfusionIO/python3-cyberfusion-rabbitmq-consumer
Requires-Dist: cryptography==43.0.0
Requires-Dist: docopt==0.6.2
Requires-Dist: pika==1.3.2
Requires-Dist: pydantic==2.10.6
Requires-Dist: PyYAML==6.0.2
Requires-Dist: schema==0.7.7
Requires-Dist: sdnotify==0.3.2
Requires-Dist: python3-cyberfusion-common~=2.12
Requires-Dist: python3-cyberfusion-systemd-support~=2.3.1
Requires-Dist: requests==2.32.3
